serial_triggers-0.1.12.dist-info/METADATA
serial_triggers-0.1.12.dist-info/WHEEL
serial_triggers/__init__.py
serial_triggers/serial_triggers.pyd
serial_triggers-0.1.12.dist-info/RECORD
